ml_engines/__init__.py
ml_engines/graphs/__init__.py
ml_engines/scripts/__init__.py
ml_engines/scripts/kaggle_downloader.py
ml_engines/supervised/__init__.py
ml_engines/supervised/classfication.py
ml_engines/unsupervised/__init__.py
ml_engines/utils/__init__.py
ml_engines/utils/constants.py
ml_engines/utils/helpers.py
ml_engines/utils/ml_tools.py
ml_engines/utils/nlp/__init__.py
ml_engines/utils/nlp/sentiment_analysis.py
tests/__init__.py
tests/unit/__init__.py
tests/unit/test_classification.py
orionmlengines_pkg_rioatmadja2018-0.1.1601955809.dist-info/METADATA
orionmlengines_pkg_rioatmadja2018-0.1.1601955809.dist-info/WHEEL
orionmlengines_pkg_rioatmadja2018-0.1.1601955809.dist-info/top_level.txt
orionmlengines_pkg_rioatmadja2018-0.1.1601955809.dist-info/zip-safe
orionmlengines_pkg_rioatmadja2018-0.1.1601955809.dist-info/RECORD
