Metadata-Version: 2.1
Name: orionmlengines-pkg-rioatmadja2018
Version: 0.1.1601955809
Summary: ML Engines to support ORION Project.
Home-page: UNKNOWN
Author: Rio Atmadja
Author-email: rioatmadja2018@gmail.com
License: UNKNOWN
Platform: UNKNOWN
Classifier: Programming Language :: Python :: 3
Classifier: Operating System :: OS Independent
Classifier: Intended Audience :: Developers
Requires-Python: >=3.6
Requires-Dist: pandas
Requires-Dist: numpy
Requires-Dist: sklearn
Requires-Dist: seaborn
Requires-Dist: botocore
